granslate/__init__.py
granslate/client.py
granslate/constants.py
granslate/gtoken.py
granslate/models.py
granslate/urls.py
granslate/utils.py
granslate-3.4.2.data/scripts/translate
granslate-3.4.2.dist-info/LICENSE
granslate-3.4.2.dist-info/METADATA
granslate-3.4.2.dist-info/WHEEL
granslate-3.4.2.dist-info/top_level.txt
granslate-3.4.2.dist-info/RECORD
