Metadata-Version: 2.1
Name: granslate
Version: 3.4.2
Summary: Free Google Translate API for Python. Translates totally free of charge.
Home-page: https://github.com/adityaprasad502/yafgt
Author: Simone
License: MIT
Keywords: google translate translator
Classifier: Development Status :: 5 - Production/Stable
Classifier: Intended Audience :: Education
Classifier: Intended Audience :: End Users/Desktop
Classifier: License :: Freeware
Classifier: Operating System :: POSIX
Classifier: Operating System :: Microsoft :: Windows
Classifier: Operating System :: MacOS :: MacOS X
Classifier: Topic :: Education
Classifier: Programming Language :: Python
Classifier: Programming Language :: Python :: 3.10
License-File: LICENSE
Requires-Dist: httpx[http2]==0.25.2
